{
  "type": "FeatureCollection",
  "features": [
    {
      "type": "Feature",
      "properties": {
        "stroke": "#e32400",
        "stroke-width": 2,
        "stroke-opacity": 1,
        "title": "Aita2"
      },
      "geometry": {
        "coordinates": [
          [
            24.576950090544443,
            65.76768645148456
          ],
          [
            24.57602572581652,
            65.76952838807267
          ],
          [
            24.574794397360648,
            65.76956969044957
          ],
          [
            24.57587682751904,
            65.77294254981751
          ],
          [
            24.576605699161718,
            65.77536275056093
          ],
          [
            24.574703167308627,
            65.77640823753279
          ],
          [
            24.572449187832063,
            65.77698175249043
          ]
        ],
        "type": "LineString"
      },
      "id": 2
    },
    {
      "type": "Feature",
      "properties": {
        "stroke": "#0056d6",
        "stroke-width": 2,
        "stroke-opacity": 1,
        "fill": "#0056d6",
        "fill-opacity": 0.2
      },
      "geometry": {
        "coordinates": [
          [
            [
              24.570477300561123,
              65.78034593749359
            ],
            [
              24.569400217004585,
              65.77993393115923
            ],
            [
              24.56896356150807,
              65.77973091112275
            ],
            [
              24.568730678577595,
              65.77922335403531
            ],
            [
              24.56871612339475,
              65.77872175838849
            ],
            [
              24.56896356150807,
              65.77827986842178
            ],
            [
              24.56976409658438,
              65.77798128983113
            ],
            [
              24.571292390820304,
              65.77795143178182
            ],
            [
              24.572820685057422,
              65.777897687206
            ],
            [
              24.573388337201976,
              65.77944429187846
            ],
            [
              24.57516406955247,
              65.78007126733584
            ],
            [
              24.573461113117474,
              65.78039967696469
            ],
            [
              24.571496163385063,
              65.78050715557092
            ],
            [
              24.570477300561123,
              65.78034593749359
            ]
          ]
        ],
        "type": "Polygon"
      },
      "id": 1
    },
    {
      "type": "Feature",
      "properties": {
        "stroke": "#e32400",
        "stroke-width": 2,
        "stroke-opacity": 1,
        "title": "Aita1"
      },
      "geometry": {
        "coordinates": [
          [
            24.572631147453592,
            65.77757608753438
          ],
          [
            24.57296747505245,
            65.77769852772636
          ],
          [
            24.57353431650023,
            65.77941489425803
          ],
          [
            24.57566515897028,
            65.78006341624805
          ]
        ],
        "type": "LineString"
      },
      "id": 3
    },
    {
      "type": "Feature",
      "properties": {
        "stroke": "#0056d6",
        "stroke-width": 2,
        "stroke-opacity": 1,
        "fill": "#0056d6",
        "fill-opacity": 0.2
      },
      "geometry": {
        "coordinates": [
          [
            [
              24.576189441987793,
              65.77355216496511
            ],
            [
              24.57889503735464,
              65.77339854848421
            ],
            [
              24.5804808512612,
              65.7784099455753
            ],
            [
              24.576635162249772,
              65.77850768262172
            ],
            [
              24.573351011898666,
              65.77732783208177
            ],
            [
              24.576771292833854,
              65.77538689536246
            ],
            [
              24.576189441987793,
              65.77355216496511
            ]
          ]
        ],
        "type": "Polygon"
      },
      "id": 3
    }
  ]
}
