{
  "type": "FeatureCollection",
  "features": [
    {
      "type": "Feature",
      "properties": {
        "stroke": "#ff4013",
        "stroke-width": 2,
        "stroke-opacity": 1,
        "fill": "#ff4013",
        "fill-opacity": 0.3
      },
      "geometry": {
        "coordinates": [
          [
            [
              25.683213831121094,
              61.14248376663264
            ],
            [
              25.683518728430812,
              61.14213528943438
            ],
            [
              25.704316833189637,
              61.14623669000753
            ],
            [
              25.703991527078216,
              61.146563348608225
            ],
            [
              25.689978948209028,
              61.143785703978295
            ],
            [
              25.691056866906415,
              61.1491004086088
            ],
            [
              25.69081366452555,
              61.14910589684328
            ],
            [
              25.68974636469872,
              61.14373350365699
            ],
            [
              25.683213831121094,
              61.14248376663264
            ]
          ]
        ],
        "type": "Polygon"
      }
    },
    {
      "type": "Feature",
      "properties": {
        "stroke": "#0061ff",
        "stroke-width": 2,
        "stroke-opacity": 1,
        "fill": "#0061ff",
        "fill-opacity": 0.3
      },
      "geometry": {
        "type": "Polygon",
        "coordinates": [
          [
            [
              25.691421198747832,
              61.14534814754185
            ],
            [
              25.70004290498207,
              61.146971852668
            ],
            [
              25.695516476206222,
              61.14891017356362
            ],
            [
              25.695206720802673,
              61.14874624073025
            ],
            [
              25.692023638543162,
              61.148822546501094
            ],
            [
              25.691421198747832,
              61.14534814754185
            ]
          ],
          [
            [
              25.69367491298371,
              61.14653016968191
            ],
            [
              25.69526500213675,
              61.14685562629046
            ],
            [
              25.69543749964066,
              61.146664733600915
            ],
            [
              25.693840925618474,
              61.14632926084636
            ],
            [
              25.69367491298371,
              61.14653016968191
            ]
          ]
        ]
      },
      "id": 1
    },
    {
      "type": "Feature",
      "properties": {
        "stroke": "#fffc41",
        "stroke-width": 2,
        "stroke-opacity": 1,
        "fill": "#fffc41",
        "fill-opacity": 0.3
      },
      "geometry": {
        "coordinates": [
          [
            [
              25.693719779760926,
              61.14651706033081
            ],
            [
              25.693857496363847,
              61.14634835854585
            ],
            [
              25.69540756267449,
              61.14667231078769
            ],
            [
              25.695255721292796,
              61.146837176759846
            ],
            [
              25.693719779760926,
              61.14651706033081
            ]
          ]
        ],
        "type": "Polygon"
      },
      "id": 2
    }
  ]
}
